[{"MMSI":"417222474","LAT":"6.955962","LON":"79.847530","SPEED":"0","HEADING":"33","COURSE":"215","STATUS":"5","TIMESTAMP":"2022-07-21T17:04:22"},{"MMSI":"417222435","LAT":"6.959742","LON":"79.855740","SPEED":"0","HEADING":"511","COURSE":"52","STATUS":"0","TIMESTAMP":"2022-07-21T17:04:18"},{"MMSI":"417222418","LAT":"6.958205","LON":"79.855960","SPEED":"0","HEADING":"511","COURSE":"10","STATUS":"0","TIMESTAMP":"2022-07-21T17:04:08"},{"MMSI":"636019337","LAT":"6.969328","LON":"79.738840","SPEED":"8","HEADING":"240","COURSE":"330","STATUS":"0","TIMESTAMP":"2022-07-21T17:04:08"},{"MMSI":"417222470","LAT":"6.960165","LON":"79.839860","SPEED":"0","HEADING":"511","COURSE":"19","STATUS":"15","TIMESTAMP":"2022-07-21T17:04:07"},{"MMSI":"412472870","LAT":"6.986995","LON":"79.815150","SPEED":"11","HEADING":"250","COURSE":"263","STATUS":"3","TIMESTAMP":"2022-07-21T17:04:07"},{"MMSI":"220596000","LAT":"6.946017","LON":"79.833630","SPEED":"0","HEADING":"270","COURSE":"164","STATUS":"5","TIMESTAMP":"2022-07-21T17:04:07"},{"MMSI":"417182341","LAT":"7.008005","LON":"79.865940","SPEED":"1","HEADING":"228","COURSE":"228","STATUS":"99","TIMESTAMP":"2022-07-21T17:04:07"},{"MMSI":"636092839","LAT":"6.948355","LON":"79.846110","SPEED":"0","HEADING":"189","COURSE":"198","STATUS":"5","TIMESTAMP":"2022-07-21T17:03:58"},{"MMSI":"417024032","LAT":"7.007155","LON":"79.866670","SPEED":"0","HEADING":"292","COURSE":"292","STATUS":"99","TIMESTAMP":"2022-07-21T17:03:54"},{"MMSI":"215091000","LAT":"6.957457","LON":"79.849110","SPEED":"0","HEADING":"34","COURSE":"299","STATUS":"5","TIMESTAMP":"2022-07-21T17:03:53"},{"MMSI":"417050832","LAT":"7.083412","LON":"79.629780","SPEED":"3","HEADING":"511","COURSE":"95","STATUS":"99","TIMESTAMP":"2022-07-21T17:03:51"},{"MMSI":"417222453","LAT":"6.959323","LON":"79.840640","SPEED":"0","HEADING":"511","COURSE":"0","STATUS":"0","TIMESTAMP":"2022-07-21T17:03:48"},{"MMSI":"538003191","LAT":"7.001333","LON":"79.729000","SPEED":"1","HEADING":"240","COURSE":"340","STATUS":"1","TIMESTAMP":"2022-07-21T17:03:41"},{"MMSI":"111000000","LAT":"6.960093","LON":"79.839230","SPEED":"0","HEADING":"511","COURSE":"256","STATUS":"15","TIMESTAMP":"2022-07-21T17:03:41"},{"MMSI":"564032000","LAT":"6.946833","LON":"79.845880","SPEED":"0","HEADING":"188","COURSE":"85","STATUS":"5","TIMESTAMP":"2022-07-21T17:03:39"},{"MMSI":"636017245","LAT":"6.980494","LON":"79.706160","SPEED":"5","HEADING":"239","COURSE":"336","STATUS":"1","TIMESTAMP":"2022-07-21T17:03:26"},{"MMSI":"417078832","LAT":"7.006392","LON":"79.865970","SPEED":"1","HEADING":"349","COURSE":"349","STATUS":"99","TIMESTAMP":"2022-07-21T17:03:24"},{"MMSI":"417222399","LAT":"6.938860","LON":"79.845000","SPEED":"0","HEADING":"511","COURSE":"230","STATUS":"99","TIMESTAMP":"2022-07-21T17:03:16"},{"MMSI":"405000337","LAT":"6.997300","LON":"79.713170","SPEED":"0","HEADING":"232","COURSE":"156","STATUS":"1","TIMESTAMP":"2022-07-21T17:03:14"},{"MMSI":"538006928","LAT":"6.956560","LON":"79.857960","SPEED":"0","HEADING":"511","COURSE":"7","STATUS":"5","TIMESTAMP":"2022-07-21T17:03:07"},{"MMSI":"352001194","LAT":"6.957817","LON":"79.854200","SPEED":"1","HEADING":"78","COURSE":"22","STATUS":"5","TIMESTAMP":"2022-07-21T17:03:01"},{"MMSI":"417222424","LAT":"6.960299","LON":"79.853520","SPEED":"0","HEADING":"86","COURSE":"0","STATUS":"0","TIMESTAMP":"2022-07-21T17:02:59"},{"MMSI":"417088732","LAT":"6.895832","LON":"79.646210","SPEED":"41","HEADING":"511","COURSE":"195","STATUS":"15","TIMESTAMP":"2022-07-21T17:02:50"},{"MMSI":"352980849","LAT":"6.958128","LON":"79.856050","SPEED":"1","HEADING":"72","COURSE":"359","STATUS":"5","TIMESTAMP":"2022-07-21T17:02:47"},{"MMSI":"538009877","LAT":"6.946183","LON":"79.851670","SPEED":"0","HEADING":"26","COURSE":"74","STATUS":"5","TIMESTAMP":"2022-07-21T17:02:46"},{"MMSI":"417222443","LAT":"6.960460","LON":"79.853490","SPEED":"0","HEADING":"93","COURSE":"36","STATUS":"1","TIMESTAMP":"2022-07-21T17:02:45"},{"MMSI":"636020978","LAT":"6.987361","LON":"79.735330","SPEED":"8","HEADING":"225","COURSE":"120","STATUS":"1","TIMESTAMP":"2022-07-21T17:02:35"},{"MMSI":"417222310","LAT":"6.939448","LON":"79.843830","SPEED":"0","HEADING":"263","COURSE":"263","STATUS":"96","TIMESTAMP":"2022-07-21T17:02:29"},{"MMSI":"417222398","LAT":"6.939212","LON":"79.845130","SPEED":"0","HEADING":"511","COURSE":"118","STATUS":"99","TIMESTAMP":"2022-07-21T17:02:26"},{"MMSI":"417222491","LAT":"6.953363","LON":"79.854710","SPEED":"0","HEADING":"157","COURSE":"73","STATUS":"0","TIMESTAMP":"2022-07-21T17:02:24"},{"MMSI":"417230440","LAT":"6.956527","LON":"79.854420","SPEED":"1","HEADING":"511","COURSE":"42","STATUS":"0","TIMESTAMP":"2022-07-21T17:02:20"},{"MMSI":"413054710","LAT":"6.946619","LON":"79.742530","SPEED":"5","HEADING":"230","COURSE":"304","STATUS":"1","TIMESTAMP":"2022-07-21T17:02:15"},{"MMSI":"417222463","LAT":"6.956435","LON":"79.854140","SPEED":"0","HEADING":"511","COURSE":"0","STATUS":"5","TIMESTAMP":"2022-07-21T17:02:14"},{"MMSI":"563191000","LAT":"6.950177","LON":"79.846390","SPEED":"0","HEADING":"189","COURSE":"196","STATUS":"5","TIMESTAMP":"2022-07-21T17:02:09"},{"MMSI":"256773000","LAT":"6.959094","LON":"79.853830","SPEED":"0","HEADING":"77","COURSE":"139","STATUS":"5","TIMESTAMP":"2022-07-21T17:02:06"},{"MMSI":"419000174","LAT":"6.954772","LON":"79.854450","SPEED":"0","HEADING":"96","COURSE":"217","STATUS":"15","TIMESTAMP":"2022-07-21T17:02:05"},{"MMSI":"620989000","LAT":"6.968783","LON":"79.639950","SPEED":"2","HEADING":"244","COURSE":"137","STATUS":"1","TIMESTAMP":"2022-07-21T17:02:01"},{"MMSI":"255802590","LAT":"7.015163","LON":"79.832330","SPEED":"1","HEADING":"225","COURSE":"46","STATUS":"5","TIMESTAMP":"2022-07-21T17:02:01"},{"MMSI":"417222374","LAT":"6.956567","LON":"79.854980","SPEED":"0","HEADING":"87","COURSE":"82","STATUS":"0","TIMESTAMP":"2022-07-21T17:02:00"}]